<DataFile name="../SpinB_MEG_NA_th0.090_10.00s_331189_saxs.tiff">
  <protocol end_timestamp="1524020765.5645401" infile="../SpinB_MEG_NA_th0.090_10.00s_331189_saxs.tiff" name="q_image" outfile="./results/SpinB_MEG_NA_th0.090_10.00s_331189_saxs.xml" output_dir="./results" runtime="0.8440492153167725" save_timestamp="1524020765.564693" start_timestamp="1524020764.720491" />
  <protocol end_timestamp="1524020766.115142" infile="../SpinB_MEG_NA_th0.090_10.00s_331189_saxs.tiff" name="thumbnails" outfile="./results/SpinB_MEG_NA_th0.090_10.00s_331189_saxs.xml" output_dir="./results" runtime="0.5496418476104736" save_timestamp="1524020766.115945" start_timestamp="1524020765.5655003">
    <result name="files_saved" type="list">
      <element index="0" value="{'filename': './thumbnails/SpinB_MEG_NA_th0.090_10.00s_331189_saxs.jpg', 'description': 'quick view (thumbnail) image', 'type': 'plot'}" />
    </result>
  </protocol>
<protocol end_timestamp="1524058439.4288375" infile="../SpinB_MEG_NA_th0.090_10.00s_331189_saxs.tiff" name="linecut_qr" outfile="./results/SpinB_MEG_NA_th0.090_10.00s_331189_saxs.xml" output_dir="./results" runtime="0.35117340087890625" save_timestamp="1524058439.4295251" start_timestamp="1524058439.0776641" /><protocol end_timestamp="1524058440.1809673" infile="../SpinB_MEG_NA_th0.090_10.00s_331189_saxs.tiff" name="q_image" outfile="./results/SpinB_MEG_NA_th0.090_10.00s_331189_saxs.xml" output_dir="./results" runtime="0.7501914501190186" save_timestamp="1524058440.1812518" start_timestamp="1524058439.430776" /></DataFile>